adi/QuadMxFE_multi.py
adi/__init__.py
adi/ad2s1210.py
adi/ad3552r.py
adi/ad4020.py
adi/ad405x.py
adi/ad4110.py
adi/ad4130.py
adi/ad4170.py
adi/ad4630.py
adi/ad469x.py
adi/ad4858.py
adi/ad5592r.py
adi/ad5627.py
adi/ad5686.py
adi/ad5754r.py
adi/ad579x.py
adi/ad5940.py
adi/ad6676.py
adi/ad7124.py
adi/ad7134.py
adi/ad717x.py
adi/ad719x.py
adi/ad7291.py
adi/ad738x.py
adi/ad7606.py
adi/ad7689.py
adi/ad7746.py
adi/ad7768.py
adi/ad777x.py
adi/ad7799.py
adi/ad9081.py
adi/ad9081_mc.py
adi/ad9083.py
adi/ad9084.py
adi/ad9084_mc.py
adi/ad9094.py
adi/ad9136.py
adi/ad9144.py
adi/ad9152.py
adi/ad9162.py
adi/ad9166.py
adi/ad9172.py
adi/ad9213.py
adi/ad9250.py
adi/ad9265.py
adi/ad936x.py
adi/ad937x.py
adi/ad9434.py
adi/ad9467.py
adi/ad9625.py
adi/ad9680.py
adi/ad9739a.py
adi/ada4961.py
adi/adaq8092.py
adi/adar1000.py
adi/adf4159.py
adi/adf4355.py
adi/adf4371.py
adi/adf5610.py
adi/adg2128.py
adi/adis16460.py
adi/adis16475.py
adi/adis16480.py
adi/adis16507.py
adi/adl5240.py
adi/adl5960.py
adi/admv8818.py
adi/adpd1080.py
adi/adpd188.py
adi/adpd410x.py
adi/adrf5720.py
adi/adrv9002.py
adi/adrv9009.py
adi/adrv9009_zu11eg.py
adi/adrv9009_zu11eg_fmcomms8.py
adi/adrv9009_zu11eg_multi.py
adi/adt7420.py
adi/adxl313.py
adi/adxl345.py
adi/adxl355.py
adi/adxrs290.py
adi/attribute.py
adi/cn0511.py
adi/cn0532.py
adi/cn0540.py
adi/cn0554.py
adi/cn0556.py
adi/cn0565.py
adi/cn0566.py
adi/cn0575.py
adi/cn0579.py
adi/compat.py
adi/context_manager.py
adi/daq2.py
adi/daq3.py
adi/dds.py
adi/dsp.py
adi/fmc_vna.py
adi/fmcadc3.py
adi/fmcjesdadc1.py
adi/fmclidar1.py
adi/fmcomms11.py
adi/fmcomms5.py
adi/gen_mux.py
adi/jesd.py
adi/jesd_internal.py
adi/lm75.py
adi/ltc2314_14.py
adi/ltc2387.py
adi/ltc2499.py
adi/ltc2664.py
adi/ltc2672.py
adi/ltc2688.py
adi/ltc2983.py
adi/max11205.py
adi/max14001.py
adi/max31855.py
adi/max31865.py
adi/max9611.py
adi/obs.py
adi/one_bit_adc_dac.py
adi/rx_tx.py
adi/sshfs.py
adi/sync_start.py
adi/tdd.py
adi/tddn.py
pyadi_iio-0.0.18.dist-info/LICENSE
pyadi_iio-0.0.18.dist-info/METADATA
pyadi_iio-0.0.18.dist-info/WHEEL
pyadi_iio-0.0.18.dist-info/top_level.txt
pyadi_iio-0.0.18.dist-info/RECORD
