Metadata-Version: 2.1
Name: pyadi-iio
Version: 0.0.18
Summary: Analog Devices python interfaces for hardware with Industrial I/O drivers
Author-email: Travis Collins <travis.collins@analog.com>
Maintainer: Analog Devices, Inc
Maintainer-email: Travis Collins <travis.collins@analog.com>
License: ADI BSD
Project-URL: homepage, https://analogdevicesinc.github.io/pyadi-iio/
Project-URL: documentation, https://analogdevicesinc.github.io/pyadi-iio/
Project-URL: repository, https://github/analogdevicesinc/pyadi-iio
Classifier: Intended Audience :: Developers
Classifier: Operating System :: OS Independent
Classifier: Programming Language :: Python :: 3
Classifier: Programming Language :: Python :: 3.7
Classifier: Programming Language :: Python :: 3.8
Classifier: Programming Language :: Python :: 3.9
Classifier: Programming Language :: Python :: 3.10
Classifier: Programming Language :: Python :: 3.11
Classifier: Topic :: Software Development :: Libraries :: Python Modules
Requires-Python: >=3.7
License-File: LICENSE
Requires-Dist: numpy >=1.20
Requires-Dist: pylibiio >=0.25
Provides-Extra: jesd
Requires-Dist: paramiko ; extra == 'jesd'
